[
  {
    "LocusId": "TA_repeats1",
    "LocusStructure": "(TA)*",
    "ReferenceRegion": "chr15:22372637-22372758",
    "VariantType": "Repeat"
  },
  {
    "LocusId": "TA_repeats2",
    "LocusStructure": "(TA)*",
    "ReferenceRegion": "chr15:22383901-22384040",
    "VariantType": "Repeat"
  },
  {
    "LocusId": "TA_repeats3",
    "LocusStructure": "(TA)*",
    "ReferenceRegion": "chr15:24586127-24586161",
    "VariantType": "Repeat"
  },
  {
    "LocusId": "TA_repeats4",
    "LocusStructure": "(TA)*",
    "ReferenceRegion": "chr15:25376971-25377026",
    "VariantType": "Repeat"
  },
  {
    "LocusId": "TA_repeats5",
    "LocusStructure": "(TA)*",
    "ReferenceRegion": "chr15:25404275-25404355",
    "VariantType": "Repeat"
  },
  {
    "LocusId": "TA_repeats6",
    "LocusStructure": "(TA)*",
    "ReferenceRegion": "chr15:25643914-25643977",
    "VariantType": "Repeat"
  },
  {
    "LocusId": "TA_repeats7",
    "LocusStructure": "(TA)*",
    "ReferenceRegion": "chr15:26640438-26640478",
    "VariantType": "Repeat"
  },
  {
    "LocusId": "TA_repeats8",
    "LocusStructure": "(TA)*",
    "ReferenceRegion": "chr15:26755721-26755907",
    "VariantType": "Repeat"
  },
  {
    "LocusId": "TA_repeats9",
    "LocusStructure": "(TA)*",
    "ReferenceRegion": "chr15:26799168-26799356",
    "VariantType": "Repeat"
  },
  {
    "LocusId": "TA_repeats10",
    "LocusStructure": "(TA)*",
    "ReferenceRegion": "chr15:26880116-26880169",
    "VariantType": "Repeat"
  },
  {
    "LocusId": "TA_repeats11",
    "LocusStructure": "(TA)*",
    "ReferenceRegion": "chr15:27550637-27550809",
    "VariantType": "Repeat"
  },
  {
    "LocusId": "TA_repeats12",
    "LocusStructure": "(TA)*",
    "ReferenceRegion": "chr15:27550853-27551551",
    "VariantType": "Repeat"
  },
  {
    "LocusId": "TA_repeats13",
    "LocusStructure": "(TA)*",
    "ReferenceRegion": "chr15:27551617-27552536",
    "VariantType": "Repeat"
  },
  {
    "LocusId": "TA_repeats14",
    "LocusStructure": "(TA)*",
    "ReferenceRegion": "chr15:27552923-27553165",
    "VariantType": "Repeat"
  },
  {
    "LocusId": "TA_repeats15",
    "LocusStructure": "(TA)*",
    "ReferenceRegion": "chr15:27553178-27553354",
    "VariantType": "Repeat"
  },
  {
    "LocusId": "TA_repeats16",
    "LocusStructure": "(TA)*",
    "ReferenceRegion": "chr15:27553388-27553559",
    "VariantType": "Repeat"
  },
  {
    "LocusId": "TA_repeats17",
    "LocusStructure": "(TA)*",
    "ReferenceRegion": "chr15:27553584-27553743",
    "VariantType": "Repeat"
  },
  {
    "LocusId": "TA_repeats18",
    "LocusStructure": "(TA)*",
    "ReferenceRegion": "chr15:27553932-27554105",
    "VariantType": "Repeat"
  },
  {
    "LocusId": "TA_repeats19",
    "LocusStructure": "(TA)*",
    "ReferenceRegion": "chr15:27554155-27554327",
    "VariantType": "Repeat"
  },
  {
    "LocusId": "TA_repeats20",
    "LocusStructure": "(TA)*",
    "ReferenceRegion": "chr15:27558326-27558457",
    "VariantType": "Repeat"
  },
  {
    "LocusId": "TA_repeats21",
    "LocusStructure": "(TA)*",
    "ReferenceRegion": "chr15:27925931-27926011",
    "VariantType": "Repeat"
  },
  {
    "LocusId": "TA_repeats22",
    "LocusStructure": "(TA)*",
    "ReferenceRegion": "chr15:27975878-27975924",
    "VariantType": "Repeat"
  },
  {
    "LocusId": "TA_repeats23",
    "LocusStructure": "(TA)*",
    "ReferenceRegion": "chr15:28069748-28069786",
    "VariantType": "Repeat"
  },
  {
    "LocusId": "TA_repeats24",
    "LocusStructure": "(TA)*",
    "ReferenceRegion": "chr15:28975845-28975894",
    "VariantType": "Repeat"
  },
  {
    "LocusId": "TA_repeats25",
    "LocusStructure": "(TA)*",
    "ReferenceRegion": "chr15:29511814-29511868",
    "VariantType": "Repeat"
  },
  {
    "LocusId": "TA_repeats26",
    "LocusStructure": "(TA)*",
    "ReferenceRegion": "chr15:30333018-30333062",
    "VariantType": "Repeat"
  },
  {
    "LocusId": "TA_repeats27",
    "LocusStructure": "(TA)*",
    "ReferenceRegion": "chr15:31582364-31582401",
    "VariantType": "Repeat"
  },
  {
    "LocusId": "TA_repeats28",
    "LocusStructure": "(TA)*",
    "ReferenceRegion": "chr15:31715348-31715401",
    "VariantType": "Repeat"
  },
  {
    "LocusId": "TA_repeats29",
    "LocusStructure": "(TA)*",
    "ReferenceRegion": "chr15:32152825-32152921",
    "VariantType": "Repeat"
  },
  {
    "LocusId": "TA_repeats30",
    "LocusStructure": "(TA)*",
    "ReferenceRegion": "chr15:33242141-33242281",
    "VariantType": "Repeat"
  },
  {
    "LocusId": "TA_repeats31",
    "LocusStructure": "(TA)*",
    "ReferenceRegion": "chr15:33756664-33756790",
    "VariantType": "Repeat"
  },
  {
    "LocusId": "TA_repeats32",
    "LocusStructure": "(TA)*",
    "ReferenceRegion": "chr15:33956746-33956829",
    "VariantType": "Repeat"
  },
  {
    "LocusId": "TA_repeats33",
    "LocusStructure": "(TA)*",
    "ReferenceRegion": "chr15:34923074-34923095",
    "VariantType": "Repeat"
  },
  {
    "LocusId": "TA_repeats34",
    "LocusStructure": "(TA)*",
    "ReferenceRegion": "chr15:35187388-35187422",
    "VariantType": "Repeat"
  },
  {
    "LocusId": "TA_repeats35",
    "LocusStructure": "(TA)*",
    "ReferenceRegion": "chr15:35835146-35835167",
    "VariantType": "Repeat"
  },
  {
    "LocusId": "TA_repeats36",
    "LocusStructure": "(TA)*",
    "ReferenceRegion": "chr15:35835429-35835504",
    "VariantType": "Repeat"
  },
  {
    "LocusId": "TA_repeats37",
    "LocusStructure": "(TA)*",
    "ReferenceRegion": "chr15:36534717-36534759",
    "VariantType": "Repeat"
  },
  {
    "LocusId": "TA_repeats38",
    "LocusStructure": "(TA)*",
    "ReferenceRegion": "chr15:36542985-36543031",
    "VariantType": "Repeat"
  },
  {
    "LocusId": "TA_repeats39",
    "LocusStructure": "(TA)*",
    "ReferenceRegion": "chr15:36694374-36694397",
    "VariantType": "Repeat"
  },
  {
    "LocusId": "TA_repeats40",
    "LocusStructure": "(TA)*",
    "ReferenceRegion": "chr15:37471157-37471202",
    "VariantType": "Repeat"
  },
  {
    "LocusId": "TA_repeats41",
    "LocusStructure": "(TA)*",
    "ReferenceRegion": "chr15:37882413-37882455",
    "VariantType": "Repeat"
  },
  {
    "LocusId": "TA_repeats42",
    "LocusStructure": "(TA)*",
    "ReferenceRegion": "chr15:38003878-38003926",
    "VariantType": "Repeat"
  },
  {
    "LocusId": "TA_repeats43",
    "LocusStructure": "(TA)*",
    "ReferenceRegion": "chr15:41581362-41581419",
    "VariantType": "Repeat"
  },
  {
    "LocusId": "TA_repeats44",
    "LocusStructure": "(TA)*",
    "ReferenceRegion": "chr15:41581870-41581924",
    "VariantType": "Repeat"
  },
  {
    "LocusId": "TA_repeats45",
    "LocusStructure": "(TA)*",
    "ReferenceRegion": "chr15:43626831-43626862",
    "VariantType": "Repeat"
  },
  {
    "LocusId": "TA_repeats46",
    "LocusStructure": "(TA)*",
    "ReferenceRegion": "chr15:44507502-44507528",
    "VariantType": "Repeat"
  },
  {
    "LocusId": "TA_repeats47",
    "LocusStructure": "(TA)*",
    "ReferenceRegion": "chr15:44508262-44508304",
    "VariantType": "Repeat"
  },
  {
    "LocusId": "TA_repeats48",
    "LocusStructure": "(TA)*",
    "ReferenceRegion": "chr15:45926396-45926423",
    "VariantType": "Repeat"
  },
  {
    "LocusId": "TA_repeats49",
    "LocusStructure": "(TA)*",
    "ReferenceRegion": "chr15:46092906-46092956",
    "VariantType": "Repeat"
  },
  {
    "LocusId": "TA_repeats50",
    "LocusStructure": "(TA)*",
    "ReferenceRegion": "chr15:47259347-47259395",
    "VariantType": "Repeat"
  },
  {
    "LocusId": "TA_repeats51",
    "LocusStructure": "(TA)*",
    "ReferenceRegion": "chr15:47273165-47273193",
    "VariantType": "Repeat"
  },
  {
    "LocusId": "TA_repeats52",
    "LocusStructure": "(TA)*",
    "ReferenceRegion": "chr15:47275631-47275678",
    "VariantType": "Repeat"
  },
  {
    "LocusId": "TA_repeats53",
    "LocusStructure": "(TA)*",
    "ReferenceRegion": "chr15:47275720-47275743",
    "VariantType": "Repeat"
  },
  {
    "LocusId": "TA_repeats54",
    "LocusStructure": "(TA)*",
    "ReferenceRegion": "chr15:47786938-47786987",
    "VariantType": "Repeat"
  },
  {
    "LocusId": "TA_repeats55",
    "LocusStructure": "(TA)*",
    "ReferenceRegion": "chr15:48088939-48088970",
    "VariantType": "Repeat"
  },
  {
    "LocusId": "TA_repeats56",
    "LocusStructure": "(TA)*",
    "ReferenceRegion": "chr15:48090014-48090049",
    "VariantType": "Repeat"
  },
  {
    "LocusId": "TA_repeats57",
    "LocusStructure": "(TA)*",
    "ReferenceRegion": "chr15:48241148-48241178",
    "VariantType": "Repeat"
  },
  {
    "LocusId": "TA_repeats58",
    "LocusStructure": "(TA)*",
    "ReferenceRegion": "chr15:48562844-48562983",
    "VariantType": "Repeat"
  },
  {
    "LocusId": "TA_repeats59",
    "LocusStructure": "(TA)*",
    "ReferenceRegion": "chr15:49384710-49384781",
    "VariantType": "Repeat"
  },
  {
    "LocusId": "TA_repeats60",
    "LocusStructure": "(TA)*",
    "ReferenceRegion": "chr15:49399834-49399986",
    "VariantType": "Repeat"
  },
  {
    "LocusId": "TA_repeats61",
    "LocusStructure": "(TA)*",
    "ReferenceRegion": "chr15:49406471-49406526",
    "VariantType": "Repeat"
  },
  {
    "LocusId": "TA_repeats62",
    "LocusStructure": "(TA)*",
    "ReferenceRegion": "chr15:49406613-49406646",
    "VariantType": "Repeat"
  },
  {
    "LocusId": "TA_repeats63",
    "LocusStructure": "(TA)*",
    "ReferenceRegion": "chr15:49412255-49412322",
    "VariantType": "Repeat"
  },
  {
    "LocusId": "TA_repeats64",
    "LocusStructure": "(TA)*",
    "ReferenceRegion": "chr15:49484666-49484722",
    "VariantType": "Repeat"
  },
  {
    "LocusId": "TA_repeats65",
    "LocusStructure": "(TA)*",
    "ReferenceRegion": "chr15:49817862-49817916",
    "VariantType": "Repeat"
  },
  {
    "LocusId": "TA_repeats66",
    "LocusStructure": "(TA)*",
    "ReferenceRegion": "chr15:49880744-49880798",
    "VariantType": "Repeat"
  },
  {
    "LocusId": "TA_repeats67",
    "LocusStructure": "(TA)*",
    "ReferenceRegion": "chr15:50448254-50448352",
    "VariantType": "Repeat"
  },
  {
    "LocusId": "TA_repeats68",
    "LocusStructure": "(TA)*",
    "ReferenceRegion": "chr15:50508807-50508858",
    "VariantType": "Repeat"
  },
  {
    "LocusId": "TA_repeats69",
    "LocusStructure": "(TA)*",
    "ReferenceRegion": "chr15:50508949-50509070",
    "VariantType": "Repeat"
  },
  {
    "LocusId": "TA_repeats70",
    "LocusStructure": "(TA)*",
    "ReferenceRegion": "chr15:51380116-51380139",
    "VariantType": "Repeat"
  },
  {
    "LocusId": "TA_repeats71",
    "LocusStructure": "(TA)*",
    "ReferenceRegion": "chr15:51996405-51996476",
    "VariantType": "Repeat"
  },
  {
    "LocusId": "TA_repeats72",
    "LocusStructure": "(TA)*",
    "ReferenceRegion": "chr15:51996957-51996995",
    "VariantType": "Repeat"
  },
  {
    "LocusId": "TA_repeats73",
    "LocusStructure": "(TA)*",
    "ReferenceRegion": "chr15:53644410-53644440",
    "VariantType": "Repeat"
  },
  {
    "LocusId": "TA_repeats74",
    "LocusStructure": "(TA)*",
    "ReferenceRegion": "chr15:53656260-53656295",
    "VariantType": "Repeat"
  },
  {
    "LocusId": "TA_repeats75",
    "LocusStructure": "(TA)*",
    "ReferenceRegion": "chr15:55566992-55567028",
    "VariantType": "Repeat"
  },
  {
    "LocusId": "TA_repeats76",
    "LocusStructure": "(TA)*",
    "ReferenceRegion": "chr15:56433854-56433882",
    "VariantType": "Repeat"
  },
  {
    "LocusId": "TA_repeats77",
    "LocusStructure": "(TA)*",
    "ReferenceRegion": "chr15:56718787-56718825",
    "VariantType": "Repeat"
  },
  {
    "LocusId": "TA_repeats78",
    "LocusStructure": "(TA)*",
    "ReferenceRegion": "chr15:56752207-56752233",
    "VariantType": "Repeat"
  },
  {
    "LocusId": "TA_repeats79",
    "LocusStructure": "(TA)*",
    "ReferenceRegion": "chr15:57128795-57128849",
    "VariantType": "Repeat"
  },
  {
    "LocusId": "TA_repeats80",
    "LocusStructure": "(TA)*",
    "ReferenceRegion": "chr15:60889750-60889851",
    "VariantType": "Repeat"
  },
  {
    "LocusId": "TA_repeats81",
    "LocusStructure": "(TA)*",
    "ReferenceRegion": "chr15:60916670-60916782",
    "VariantType": "Repeat"
  },
  {
    "LocusId": "TA_repeats82",
    "LocusStructure": "(TA)*",
    "ReferenceRegion": "chr15:61332312-61332363",
    "VariantType": "Repeat"
  },
  {
    "LocusId": "TA_repeats83",
    "LocusStructure": "(TA)*",
    "ReferenceRegion": "chr15:62106099-62106138",
    "VariantType": "Repeat"
  },
  {
    "LocusId": "TA_repeats84",
    "LocusStructure": "(TA)*",
    "ReferenceRegion": "chr15:62520563-62520584",
    "VariantType": "Repeat"
  },
  {
    "LocusId": "TA_repeats85",
    "LocusStructure": "(TA)*",
    "ReferenceRegion": "chr15:64669687-64669737",
    "VariantType": "Repeat"
  },
  {
    "LocusId": "TA_repeats86",
    "LocusStructure": "(TA)*",
    "ReferenceRegion": "chr15:66013285-66013320",
    "VariantType": "Repeat"
  },
  {
    "LocusId": "TA_repeats87",
    "LocusStructure": "(TA)*",
    "ReferenceRegion": "chr15:69050157-69050216",
    "VariantType": "Repeat"
  },
  {
    "LocusId": "TA_repeats88",
    "LocusStructure": "(TA)*",
    "ReferenceRegion": "chr15:70278284-70278327",
    "VariantType": "Repeat"
  },
  {
    "LocusId": "TA_repeats89",
    "LocusStructure": "(TA)*",
    "ReferenceRegion": "chr15:70896255-70896384",
    "VariantType": "Repeat"
  },
  {
    "LocusId": "TA_repeats90",
    "LocusStructure": "(TA)*",
    "ReferenceRegion": "chr15:71465016-71465073",
    "VariantType": "Repeat"
  },
  {
    "LocusId": "TA_repeats91",
    "LocusStructure": "(TA)*",
    "ReferenceRegion": "chr15:71465906-71465944",
    "VariantType": "Repeat"
  },
  {
    "LocusId": "TA_repeats92",
    "LocusStructure": "(TA)*",
    "ReferenceRegion": "chr15:71619039-71619065",
    "VariantType": "Repeat"
  },
  {
    "LocusId": "TA_repeats93",
    "LocusStructure": "(TA)*",
    "ReferenceRegion": "chr15:71734919-71735042",
    "VariantType": "Repeat"
  },
  {
    "LocusId": "TA_repeats94",
    "LocusStructure": "(TA)*",
    "ReferenceRegion": "chr15:72016605-72016627",
    "VariantType": "Repeat"
  },
  {
    "LocusId": "TA_repeats95",
    "LocusStructure": "(TA)*",
    "ReferenceRegion": "chr15:72019892-72019927",
    "VariantType": "Repeat"
  },
  {
    "LocusId": "TA_repeats96",
    "LocusStructure": "(TA)*",
    "ReferenceRegion": "chr15:72220368-72220398",
    "VariantType": "Repeat"
  },
  {
    "LocusId": "TA_repeats97",
    "LocusStructure": "(TA)*",
    "ReferenceRegion": "chr15:73333118-73333188",
    "VariantType": "Repeat"
  },
  {
    "LocusId": "TA_repeats98",
    "LocusStructure": "(TA)*",
    "ReferenceRegion": "chr15:73606262-73606283",
    "VariantType": "Repeat"
  },
  {
    "LocusId": "TA_repeats99",
    "LocusStructure": "(TA)*",
    "ReferenceRegion": "chr15:74010575-74010622",
    "VariantType": "Repeat"
  },
  {
    "LocusId": "TA_repeats100",
    "LocusStructure": "(TA)*",
    "ReferenceRegion": "chr15:76721202-76721235",
    "VariantType": "Repeat"
  },
  {
    "LocusId": "TA_repeats101",
    "LocusStructure": "(TA)*",
    "ReferenceRegion": "chr15:77018465-77018496",
    "VariantType": "Repeat"
  },
  {
    "LocusId": "TA_repeats102",
    "LocusStructure": "(TA)*",
    "ReferenceRegion": "chr15:77518008-77518039",
    "VariantType": "Repeat"
  },
  {
    "LocusId": "TA_repeats103",
    "LocusStructure": "(TA)*",
    "ReferenceRegion": "chr15:77518386-77518455",
    "VariantType": "Repeat"
  },
  {
    "LocusId": "TA_repeats104",
    "LocusStructure": "(TA)*",
    "ReferenceRegion": "chr15:80008822-80008960",
    "VariantType": "Repeat"
  },
  {
    "LocusId": "TA_repeats105",
    "LocusStructure": "(TA)*",
    "ReferenceRegion": "chr15:81769007-81769038",
    "VariantType": "Repeat"
  },
  {
    "LocusId": "TA_repeats106",
    "LocusStructure": "(TA)*",
    "ReferenceRegion": "chr15:81910966-81911027",
    "VariantType": "Repeat"
  },
  {
    "LocusId": "TA_repeats107",
    "LocusStructure": "(TA)*",
    "ReferenceRegion": "chr15:81927740-81927926",
    "VariantType": "Repeat"
  },
  {
    "LocusId": "TA_repeats108",
    "LocusStructure": "(TA)*",
    "ReferenceRegion": "chr15:81957424-81957500",
    "VariantType": "Repeat"
  },
  {
    "LocusId": "TA_repeats109",
    "LocusStructure": "(TA)*",
    "ReferenceRegion": "chr15:82296767-82296871",
    "VariantType": "Repeat"
  },
  {
    "LocusId": "TA_repeats110",
    "LocusStructure": "(TA)*",
    "ReferenceRegion": "chr15:83446879-83446910",
    "VariantType": "Repeat"
  },
  {
    "LocusId": "TA_repeats111",
    "LocusStructure": "(TA)*",
    "ReferenceRegion": "chr15:84343371-84343541",
    "VariantType": "Repeat"
  },
  {
    "LocusId": "TA_repeats112",
    "LocusStructure": "(TA)*",
    "ReferenceRegion": "chr15:84470378-84470455",
    "VariantType": "Repeat"
  },
  {
    "LocusId": "TA_repeats113",
    "LocusStructure": "(TA)*",
    "ReferenceRegion": "chr15:86841473-86841631",
    "VariantType": "Repeat"
  },
  {
    "LocusId": "TA_repeats114",
    "LocusStructure": "(TA)*",
    "ReferenceRegion": "chr15:87179933-87180000",
    "VariantType": "Repeat"
  },
  {
    "LocusId": "TA_repeats115",
    "LocusStructure": "(TA)*",
    "ReferenceRegion": "chr15:87678872-87678914",
    "VariantType": "Repeat"
  },
  {
    "LocusId": "TA_repeats116",
    "LocusStructure": "(TA)*",
    "ReferenceRegion": "chr15:88042894-88043060",
    "VariantType": "Repeat"
  },
  {
    "LocusId": "TA_repeats117",
    "LocusStructure": "(TA)*",
    "ReferenceRegion": "chr15:88429907-88429939",
    "VariantType": "Repeat"
  },
  {
    "LocusId": "TA_repeats118",
    "LocusStructure": "(TA)*",
    "ReferenceRegion": "chr15:88456162-88456204",
    "VariantType": "Repeat"
  },
  {
    "LocusId": "TA_repeats119",
    "LocusStructure": "(TA)*",
    "ReferenceRegion": "chr15:88576407-88576447",
    "VariantType": "Repeat"
  },
  {
    "LocusId": "TA_repeats120",
    "LocusStructure": "(TA)*",
    "ReferenceRegion": "chr15:89132446-89132486",
    "VariantType": "Repeat"
  },
  {
    "LocusId": "TA_repeats121",
    "LocusStructure": "(TA)*",
    "ReferenceRegion": "chr15:91560597-91560653",
    "VariantType": "Repeat"
  },
  {
    "LocusId": "TA_repeats122",
    "LocusStructure": "(TA)*",
    "ReferenceRegion": "chr15:92177997-92178035",
    "VariantType": "Repeat"
  },
  {
    "LocusId": "TA_repeats123",
    "LocusStructure": "(TA)*",
    "ReferenceRegion": "chr15:94301086-94301146",
    "VariantType": "Repeat"
  },
  {
    "LocusId": "TA_repeats124",
    "LocusStructure": "(TA)*",
    "ReferenceRegion": "chr15:95841578-95841622",
    "VariantType": "Repeat"
  },
  {
    "LocusId": "TA_repeats125",
    "LocusStructure": "(TA)*",
    "ReferenceRegion": "chr15:95911067-95911212",
    "VariantType": "Repeat"
  },
  {
    "LocusId": "TA_repeats126",
    "LocusStructure": "(TA)*",
    "ReferenceRegion": "chr15:95966820-95966912",
    "VariantType": "Repeat"
  },
  {
    "LocusId": "TA_repeats127",
    "LocusStructure": "(TA)*",
    "ReferenceRegion": "chr15:95970316-95970353",
    "VariantType": "Repeat"
  },
  {
    "LocusId": "TA_repeats128",
    "LocusStructure": "(TA)*",
    "ReferenceRegion": "chr15:97020141-97020273",
    "VariantType": "Repeat"
  },
  {
    "LocusId": "TA_repeats129",
    "LocusStructure": "(TA)*",
    "ReferenceRegion": "chr15:97020365-97020407",
    "VariantType": "Repeat"
  },
  {
    "LocusId": "TA_repeats130",
    "LocusStructure": "(TA)*",
    "ReferenceRegion": "chr15:97021492-97021534",
    "VariantType": "Repeat"
  },
  {
    "LocusId": "TA_repeats131",
    "LocusStructure": "(TA)*",
    "ReferenceRegion": "chr15:97262965-97263074",
    "VariantType": "Repeat"
  },
  {
    "LocusId": "TA_repeats132",
    "LocusStructure": "(TA)*",
    "ReferenceRegion": "chr15:97445579-97445620",
    "VariantType": "Repeat"
  },
  {
    "LocusId": "TA_repeats133",
    "LocusStructure": "(TA)*",
    "ReferenceRegion": "chr15:97445665-97445688",
    "VariantType": "Repeat"
  },
  {
    "LocusId": "TA_repeats134",
    "LocusStructure": "(TA)*",
    "ReferenceRegion": "chr15:98061430-98061582",
    "VariantType": "Repeat"
  },
  {
    "LocusId": "TA_repeats135",
    "LocusStructure": "(TA)*",
    "ReferenceRegion": "chr15:100308726-100309070",
    "VariantType": "Repeat"
  },
  {
    "LocusId": "TA_repeats136",
    "LocusStructure": "(TA)*",
    "ReferenceRegion": "chr15:100311638-100311685",
    "VariantType": "Repeat"
  },
  {
    "LocusId": "TA_repeats137",
    "LocusStructure": "(TA)*",
    "ReferenceRegion": "chr15:100487724-100487769",
    "VariantType": "Repeat"
  }
]
