[
  {
    "LocusId": "TA_repeats1",
    "LocusStructure": "(TA)*",
    "ReferenceRegion": "chr9:1249202-1249271",
    "VariantType": "Repeat"
  },
  {
    "LocusId": "TA_repeats2",
    "LocusStructure": "(TA)*",
    "ReferenceRegion": "chr9:2589009-2589139",
    "VariantType": "Repeat"
  },
  {
    "LocusId": "TA_repeats3",
    "LocusStructure": "(TA)*",
    "ReferenceRegion": "chr9:2890869-2890943",
    "VariantType": "Repeat"
  },
  {
    "LocusId": "TA_repeats4",
    "LocusStructure": "(TA)*",
    "ReferenceRegion": "chr9:3104293-3104383",
    "VariantType": "Repeat"
  },
  {
    "LocusId": "TA_repeats5",
    "LocusStructure": "(TA)*",
    "ReferenceRegion": "chr9:3165253-3165310",
    "VariantType": "Repeat"
  },
  {
    "LocusId": "TA_repeats6",
    "LocusStructure": "(TA)*",
    "ReferenceRegion": "chr9:3217705-3217742",
    "VariantType": "Repeat"
  },
  {
    "LocusId": "TA_repeats7",
    "LocusStructure": "(TA)*",
    "ReferenceRegion": "chr9:3423760-3423812",
    "VariantType": "Repeat"
  },
  {
    "LocusId": "TA_repeats8",
    "LocusStructure": "(TA)*",
    "ReferenceRegion": "chr9:3607610-3607637",
    "VariantType": "Repeat"
  },
  {
    "LocusId": "TA_repeats9",
    "LocusStructure": "(TA)*",
    "ReferenceRegion": "chr9:8145011-8145067",
    "VariantType": "Repeat"
  },
  {
    "LocusId": "TA_repeats10",
    "LocusStructure": "(TA)*",
    "ReferenceRegion": "chr9:8212091-8212168",
    "VariantType": "Repeat"
  },
  {
    "LocusId": "TA_repeats11",
    "LocusStructure": "(TA)*",
    "ReferenceRegion": "chr9:8321487-8321527",
    "VariantType": "Repeat"
  },
  {
    "LocusId": "TA_repeats12",
    "LocusStructure": "(TA)*",
    "ReferenceRegion": "chr9:10403227-10403259",
    "VariantType": "Repeat"
  },
  {
    "LocusId": "TA_repeats13",
    "LocusStructure": "(TA)*",
    "ReferenceRegion": "chr9:10523589-10523623",
    "VariantType": "Repeat"
  },
  {
    "LocusId": "TA_repeats14",
    "LocusStructure": "(TA)*",
    "ReferenceRegion": "chr9:10715628-10715674",
    "VariantType": "Repeat"
  },
  {
    "LocusId": "TA_repeats15",
    "LocusStructure": "(TA)*",
    "ReferenceRegion": "chr9:11837886-11837944",
    "VariantType": "Repeat"
  },
  {
    "LocusId": "TA_repeats16",
    "LocusStructure": "(TA)*",
    "ReferenceRegion": "chr9:11863395-11863571",
    "VariantType": "Repeat"
  },
  {
    "LocusId": "TA_repeats17",
    "LocusStructure": "(TA)*",
    "ReferenceRegion": "chr9:11864601-11864649",
    "VariantType": "Repeat"
  },
  {
    "LocusId": "TA_repeats18",
    "LocusStructure": "(TA)*",
    "ReferenceRegion": "chr9:11865911-11866236",
    "VariantType": "Repeat"
  },
  {
    "LocusId": "TA_repeats19",
    "LocusStructure": "(TA)*",
    "ReferenceRegion": "chr9:11868117-11868218",
    "VariantType": "Repeat"
  },
  {
    "LocusId": "TA_repeats20",
    "LocusStructure": "(TA)*",
    "ReferenceRegion": "chr9:11869934-11869974",
    "VariantType": "Repeat"
  },
  {
    "LocusId": "TA_repeats21",
    "LocusStructure": "(TA)*",
    "ReferenceRegion": "chr9:12412669-12412702",
    "VariantType": "Repeat"
  },
  {
    "LocusId": "TA_repeats22",
    "LocusStructure": "(TA)*",
    "ReferenceRegion": "chr9:13432731-13432775",
    "VariantType": "Repeat"
  },
  {
    "LocusId": "TA_repeats23",
    "LocusStructure": "(TA)*",
    "ReferenceRegion": "chr9:14481195-14481233",
    "VariantType": "Repeat"
  },
  {
    "LocusId": "TA_repeats24",
    "LocusStructure": "(TA)*",
    "ReferenceRegion": "chr9:15166980-15167027",
    "VariantType": "Repeat"
  },
  {
    "LocusId": "TA_repeats25",
    "LocusStructure": "(TA)*",
    "ReferenceRegion": "chr9:15311268-15311388",
    "VariantType": "Repeat"
  },
  {
    "LocusId": "TA_repeats26",
    "LocusStructure": "(TA)*",
    "ReferenceRegion": "chr9:15677849-15677924",
    "VariantType": "Repeat"
  },
  {
    "LocusId": "TA_repeats27",
    "LocusStructure": "(TA)*",
    "ReferenceRegion": "chr9:15799133-15799164",
    "VariantType": "Repeat"
  },
  {
    "LocusId": "TA_repeats28",
    "LocusStructure": "(TA)*",
    "ReferenceRegion": "chr9:17058786-17058835",
    "VariantType": "Repeat"
  },
  {
    "LocusId": "TA_repeats29",
    "LocusStructure": "(TA)*",
    "ReferenceRegion": "chr9:18399275-18399327",
    "VariantType": "Repeat"
  },
  {
    "LocusId": "TA_repeats30",
    "LocusStructure": "(TA)*",
    "ReferenceRegion": "chr9:18503419-18503439",
    "VariantType": "Repeat"
  },
  {
    "LocusId": "TA_repeats31",
    "LocusStructure": "(TA)*",
    "ReferenceRegion": "chr9:18703695-18703733",
    "VariantType": "Repeat"
  },
  {
    "LocusId": "TA_repeats32",
    "LocusStructure": "(TA)*",
    "ReferenceRegion": "chr9:18756074-18756121",
    "VariantType": "Repeat"
  },
  {
    "LocusId": "TA_repeats33",
    "LocusStructure": "(TA)*",
    "ReferenceRegion": "chr9:22403248-22403303",
    "VariantType": "Repeat"
  },
  {
    "LocusId": "TA_repeats34",
    "LocusStructure": "(TA)*",
    "ReferenceRegion": "chr9:22411816-22411955",
    "VariantType": "Repeat"
  },
  {
    "LocusId": "TA_repeats35",
    "LocusStructure": "(TA)*",
    "ReferenceRegion": "chr9:22821930-22822011",
    "VariantType": "Repeat"
  },
  {
    "LocusId": "TA_repeats36",
    "LocusStructure": "(TA)*",
    "ReferenceRegion": "chr9:22989169-22989243",
    "VariantType": "Repeat"
  },
  {
    "LocusId": "TA_repeats37",
    "LocusStructure": "(TA)*",
    "ReferenceRegion": "chr9:22992796-22992823",
    "VariantType": "Repeat"
  },
  {
    "LocusId": "TA_repeats38",
    "LocusStructure": "(TA)*",
    "ReferenceRegion": "chr9:23111371-23111399",
    "VariantType": "Repeat"
  },
  {
    "LocusId": "TA_repeats39",
    "LocusStructure": "(TA)*",
    "ReferenceRegion": "chr9:23159464-23159504",
    "VariantType": "Repeat"
  },
  {
    "LocusId": "TA_repeats40",
    "LocusStructure": "(TA)*",
    "ReferenceRegion": "chr9:23335734-23335819",
    "VariantType": "Repeat"
  },
  {
    "LocusId": "TA_repeats41",
    "LocusStructure": "(TA)*",
    "ReferenceRegion": "chr9:23573505-23573560",
    "VariantType": "Repeat"
  },
  {
    "LocusId": "TA_repeats42",
    "LocusStructure": "(TA)*",
    "ReferenceRegion": "chr9:24476368-24476447",
    "VariantType": "Repeat"
  },
  {
    "LocusId": "TA_repeats43",
    "LocusStructure": "(TA)*",
    "ReferenceRegion": "chr9:24953849-24953949",
    "VariantType": "Repeat"
  },
  {
    "LocusId": "TA_repeats44",
    "LocusStructure": "(TA)*",
    "ReferenceRegion": "chr9:24959653-24959685",
    "VariantType": "Repeat"
  },
  {
    "LocusId": "TA_repeats45",
    "LocusStructure": "(TA)*",
    "ReferenceRegion": "chr9:24990756-24990794",
    "VariantType": "Repeat"
  },
  {
    "LocusId": "TA_repeats46",
    "LocusStructure": "(TA)*",
    "ReferenceRegion": "chr9:24990865-24991043",
    "VariantType": "Repeat"
  },
  {
    "LocusId": "TA_repeats47",
    "LocusStructure": "(TA)*",
    "ReferenceRegion": "chr9:25047893-25047977",
    "VariantType": "Repeat"
  },
  {
    "LocusId": "TA_repeats48",
    "LocusStructure": "(TA)*",
    "ReferenceRegion": "chr9:25108066-25108125",
    "VariantType": "Repeat"
  },
  {
    "LocusId": "TA_repeats49",
    "LocusStructure": "(TA)*",
    "ReferenceRegion": "chr9:25186613-25186765",
    "VariantType": "Repeat"
  },
  {
    "LocusId": "TA_repeats50",
    "LocusStructure": "(TA)*",
    "ReferenceRegion": "chr9:25364865-25364894",
    "VariantType": "Repeat"
  },
  {
    "LocusId": "TA_repeats51",
    "LocusStructure": "(TA)*",
    "ReferenceRegion": "chr9:25366536-25366578",
    "VariantType": "Repeat"
  },
  {
    "LocusId": "TA_repeats52",
    "LocusStructure": "(TA)*",
    "ReferenceRegion": "chr9:25786566-25786813",
    "VariantType": "Repeat"
  },
  {
    "LocusId": "TA_repeats53",
    "LocusStructure": "(TA)*",
    "ReferenceRegion": "chr9:25883115-25883149",
    "VariantType": "Repeat"
  },
  {
    "LocusId": "TA_repeats54",
    "LocusStructure": "(TA)*",
    "ReferenceRegion": "chr9:25887557-25887956",
    "VariantType": "Repeat"
  },
  {
    "LocusId": "TA_repeats55",
    "LocusStructure": "(TA)*",
    "ReferenceRegion": "chr9:25940191-25940222",
    "VariantType": "Repeat"
  },
  {
    "LocusId": "TA_repeats56",
    "LocusStructure": "(TA)*",
    "ReferenceRegion": "chr9:25940259-25940635",
    "VariantType": "Repeat"
  },
  {
    "LocusId": "TA_repeats57",
    "LocusStructure": "(TA)*",
    "ReferenceRegion": "chr9:26332940-26333181",
    "VariantType": "Repeat"
  },
  {
    "LocusId": "TA_repeats58",
    "LocusStructure": "(TA)*",
    "ReferenceRegion": "chr9:26335469-26335543",
    "VariantType": "Repeat"
  },
  {
    "LocusId": "TA_repeats59",
    "LocusStructure": "(TA)*",
    "ReferenceRegion": "chr9:27420546-27420594",
    "VariantType": "Repeat"
  },
  {
    "LocusId": "TA_repeats60",
    "LocusStructure": "(TA)*",
    "ReferenceRegion": "chr9:27659350-27659384",
    "VariantType": "Repeat"
  },
  {
    "LocusId": "TA_repeats61",
    "LocusStructure": "(TA)*",
    "ReferenceRegion": "chr9:28506397-28506419",
    "VariantType": "Repeat"
  },
  {
    "LocusId": "TA_repeats62",
    "LocusStructure": "(TA)*",
    "ReferenceRegion": "chr9:28506504-28506520",
    "VariantType": "Repeat"
  },
  {
    "LocusId": "TA_repeats63",
    "LocusStructure": "(TA)*",
    "ReferenceRegion": "chr9:28512591-28512690",
    "VariantType": "Repeat"
  },
  {
    "LocusId": "TA_repeats64",
    "LocusStructure": "(TA)*",
    "ReferenceRegion": "chr9:28714162-28714232",
    "VariantType": "Repeat"
  },
  {
    "LocusId": "TA_repeats65",
    "LocusStructure": "(TA)*",
    "ReferenceRegion": "chr9:28795540-28795621",
    "VariantType": "Repeat"
  },
  {
    "LocusId": "TA_repeats66",
    "LocusStructure": "(TA)*",
    "ReferenceRegion": "chr9:28797272-28797358",
    "VariantType": "Repeat"
  },
  {
    "LocusId": "TA_repeats67",
    "LocusStructure": "(TA)*",
    "ReferenceRegion": "chr9:28883602-28883667",
    "VariantType": "Repeat"
  },
  {
    "LocusId": "TA_repeats68",
    "LocusStructure": "(TA)*",
    "ReferenceRegion": "chr9:29179156-29179200",
    "VariantType": "Repeat"
  },
  {
    "LocusId": "TA_repeats69",
    "LocusStructure": "(TA)*",
    "ReferenceRegion": "chr9:29371271-29371291",
    "VariantType": "Repeat"
  },
  {
    "LocusId": "TA_repeats70",
    "LocusStructure": "(TA)*",
    "ReferenceRegion": "chr9:29373515-29373622",
    "VariantType": "Repeat"
  },
  {
    "LocusId": "TA_repeats71",
    "LocusStructure": "(TA)*",
    "ReferenceRegion": "chr9:30273892-30273921",
    "VariantType": "Repeat"
  },
  {
    "LocusId": "TA_repeats72",
    "LocusStructure": "(TA)*",
    "ReferenceRegion": "chr9:30274061-30274157",
    "VariantType": "Repeat"
  },
  {
    "LocusId": "TA_repeats73",
    "LocusStructure": "(TA)*",
    "ReferenceRegion": "chr9:30493841-30493885",
    "VariantType": "Repeat"
  },
  {
    "LocusId": "TA_repeats74",
    "LocusStructure": "(TA)*",
    "ReferenceRegion": "chr9:30668174-30668249",
    "VariantType": "Repeat"
  },
  {
    "LocusId": "TA_repeats75",
    "LocusStructure": "(TA)*",
    "ReferenceRegion": "chr9:30668340-30668401",
    "VariantType": "Repeat"
  },
  {
    "LocusId": "TA_repeats76",
    "LocusStructure": "(TA)*",
    "ReferenceRegion": "chr9:31012671-31012765",
    "VariantType": "Repeat"
  },
  {
    "LocusId": "TA_repeats77",
    "LocusStructure": "(TA)*",
    "ReferenceRegion": "chr9:31134152-31134316",
    "VariantType": "Repeat"
  },
  {
    "LocusId": "TA_repeats78",
    "LocusStructure": "(TA)*",
    "ReferenceRegion": "chr9:31509684-31509733",
    "VariantType": "Repeat"
  },
  {
    "LocusId": "TA_repeats79",
    "LocusStructure": "(TA)*",
    "ReferenceRegion": "chr9:31663909-31663998",
    "VariantType": "Repeat"
  },
  {
    "LocusId": "TA_repeats80",
    "LocusStructure": "(TA)*",
    "ReferenceRegion": "chr9:31839926-31839967",
    "VariantType": "Repeat"
  },
  {
    "LocusId": "TA_repeats81",
    "LocusStructure": "(TA)*",
    "ReferenceRegion": "chr9:33174988-33175019",
    "VariantType": "Repeat"
  },
  {
    "LocusId": "TA_repeats82",
    "LocusStructure": "(TA)*",
    "ReferenceRegion": "chr9:34346357-34346434",
    "VariantType": "Repeat"
  },
  {
    "LocusId": "TA_repeats83",
    "LocusStructure": "(TA)*",
    "ReferenceRegion": "chr9:34492491-34492533",
    "VariantType": "Repeat"
  },
  {
    "LocusId": "TA_repeats84",
    "LocusStructure": "(TA)*",
    "ReferenceRegion": "chr9:37074435-37074587",
    "VariantType": "Repeat"
  },
  {
    "LocusId": "TA_repeats85",
    "LocusStructure": "(TA)*",
    "ReferenceRegion": "chr9:37814077-37814124",
    "VariantType": "Repeat"
  },
  {
    "LocusId": "TA_repeats86",
    "LocusStructure": "(TA)*",
    "ReferenceRegion": "chr9:37850823-37850879",
    "VariantType": "Repeat"
  },
  {
    "LocusId": "TA_repeats87",
    "LocusStructure": "(TA)*",
    "ReferenceRegion": "chr9:37852927-37852963",
    "VariantType": "Repeat"
  },
  {
    "LocusId": "TA_repeats88",
    "LocusStructure": "(TA)*",
    "ReferenceRegion": "chr9:38792336-38792377",
    "VariantType": "Repeat"
  },
  {
    "LocusId": "TA_repeats89",
    "LocusStructure": "(TA)*",
    "ReferenceRegion": "chr9:39022285-39022333",
    "VariantType": "Repeat"
  },
  {
    "LocusId": "TA_repeats90",
    "LocusStructure": "(TA)*",
    "ReferenceRegion": "chr9:39502246-39502289",
    "VariantType": "Repeat"
  },
  {
    "LocusId": "TA_repeats91",
    "LocusStructure": "(TA)*",
    "ReferenceRegion": "chr9:39630527-39630558",
    "VariantType": "Repeat"
  },
  {
    "LocusId": "TA_repeats92",
    "LocusStructure": "(TA)*",
    "ReferenceRegion": "chr9:39902995-39903035",
    "VariantType": "Repeat"
  },
  {
    "LocusId": "TA_repeats93",
    "LocusStructure": "(TA)*",
    "ReferenceRegion": "chr9:40080412-40080435",
    "VariantType": "Repeat"
  },
  {
    "LocusId": "TA_repeats94",
    "LocusStructure": "(TA)*",
    "ReferenceRegion": "chr9:40297225-40297339",
    "VariantType": "Repeat"
  },
  {
    "LocusId": "TA_repeats95",
    "LocusStructure": "(TA)*",
    "ReferenceRegion": "chr9:40389136-40389171",
    "VariantType": "Repeat"
  },
  {
    "LocusId": "TA_repeats96",
    "LocusStructure": "(TA)*",
    "ReferenceRegion": "chr9:40718436-40718482",
    "VariantType": "Repeat"
  },
  {
    "LocusId": "TA_repeats97",
    "LocusStructure": "(TA)*",
    "ReferenceRegion": "chr9:44178619-44178642",
    "VariantType": "Repeat"
  },
  {
    "LocusId": "TA_repeats98",
    "LocusStructure": "(TA)*",
    "ReferenceRegion": "chr9:44235875-44236223",
    "VariantType": "Repeat"
  },
  {
    "LocusId": "TA_repeats99",
    "LocusStructure": "(TA)*",
    "ReferenceRegion": "chr9:44411627-44411663",
    "VariantType": "Repeat"
  },
  {
    "LocusId": "TA_repeats100",
    "LocusStructure": "(TA)*",
    "ReferenceRegion": "chr9:44586787-44586814",
    "VariantType": "Repeat"
  },
  {
    "LocusId": "TA_repeats101",
    "LocusStructure": "(TA)*",
    "ReferenceRegion": "chr9:44904853-44904896",
    "VariantType": "Repeat"
  },
  {
    "LocusId": "TA_repeats102",
    "LocusStructure": "(TA)*",
    "ReferenceRegion": "chr9:71021576-71021648",
    "VariantType": "Repeat"
  },
  {
    "LocusId": "TA_repeats103",
    "LocusStructure": "(TA)*",
    "ReferenceRegion": "chr9:72138370-72138449",
    "VariantType": "Repeat"
  },
  {
    "LocusId": "TA_repeats104",
    "LocusStructure": "(TA)*",
    "ReferenceRegion": "chr9:72456080-72456113",
    "VariantType": "Repeat"
  },
  {
    "LocusId": "TA_repeats105",
    "LocusStructure": "(TA)*",
    "ReferenceRegion": "chr9:74116308-74116378",
    "VariantType": "Repeat"
  },
  {
    "LocusId": "TA_repeats106",
    "LocusStructure": "(TA)*",
    "ReferenceRegion": "chr9:75003094-75003201",
    "VariantType": "Repeat"
  },
  {
    "LocusId": "TA_repeats107",
    "LocusStructure": "(TA)*",
    "ReferenceRegion": "chr9:75931837-75931863",
    "VariantType": "Repeat"
  },
  {
    "LocusId": "TA_repeats108",
    "LocusStructure": "(TA)*",
    "ReferenceRegion": "chr9:76179701-76179726",
    "VariantType": "Repeat"
  },
  {
    "LocusId": "TA_repeats109",
    "LocusStructure": "(TA)*",
    "ReferenceRegion": "chr9:76680104-76680128",
    "VariantType": "Repeat"
  },
  {
    "LocusId": "TA_repeats110",
    "LocusStructure": "(TA)*",
    "ReferenceRegion": "chr9:76895454-76895474",
    "VariantType": "Repeat"
  },
  {
    "LocusId": "TA_repeats111",
    "LocusStructure": "(TA)*",
    "ReferenceRegion": "chr9:76983705-76983798",
    "VariantType": "Repeat"
  },
  {
    "LocusId": "TA_repeats112",
    "LocusStructure": "(TA)*",
    "ReferenceRegion": "chr9:77319297-77319558",
    "VariantType": "Repeat"
  },
  {
    "LocusId": "TA_repeats113",
    "LocusStructure": "(TA)*",
    "ReferenceRegion": "chr9:78079279-78079319",
    "VariantType": "Repeat"
  },
  {
    "LocusId": "TA_repeats114",
    "LocusStructure": "(TA)*",
    "ReferenceRegion": "chr9:78986560-78986668",
    "VariantType": "Repeat"
  },
  {
    "LocusId": "TA_repeats115",
    "LocusStructure": "(TA)*",
    "ReferenceRegion": "chr9:81450782-81450833",
    "VariantType": "Repeat"
  },
  {
    "LocusId": "TA_repeats116",
    "LocusStructure": "(TA)*",
    "ReferenceRegion": "chr9:81536813-81537090",
    "VariantType": "Repeat"
  },
  {
    "LocusId": "TA_repeats117",
    "LocusStructure": "(TA)*",
    "ReferenceRegion": "chr9:81537552-81537669",
    "VariantType": "Repeat"
  },
  {
    "LocusId": "TA_repeats118",
    "LocusStructure": "(TA)*",
    "ReferenceRegion": "chr9:81584293-81584346",
    "VariantType": "Repeat"
  },
  {
    "LocusId": "TA_repeats119",
    "LocusStructure": "(TA)*",
    "ReferenceRegion": "chr9:81608604-81608677",
    "VariantType": "Repeat"
  },
  {
    "LocusId": "TA_repeats120",
    "LocusStructure": "(TA)*",
    "ReferenceRegion": "chr9:81669440-81669479",
    "VariantType": "Repeat"
  },
  {
    "LocusId": "TA_repeats121",
    "LocusStructure": "(TA)*",
    "ReferenceRegion": "chr9:81671606-81671684",
    "VariantType": "Repeat"
  },
  {
    "LocusId": "TA_repeats122",
    "LocusStructure": "(TA)*",
    "ReferenceRegion": "chr9:81978523-81978548",
    "VariantType": "Repeat"
  },
  {
    "LocusId": "TA_repeats123",
    "LocusStructure": "(TA)*",
    "ReferenceRegion": "chr9:82657852-82657919",
    "VariantType": "Repeat"
  },
  {
    "LocusId": "TA_repeats124",
    "LocusStructure": "(TA)*",
    "ReferenceRegion": "chr9:82660883-82661001",
    "VariantType": "Repeat"
  },
  {
    "LocusId": "TA_repeats125",
    "LocusStructure": "(TA)*",
    "ReferenceRegion": "chr9:83177635-83177822",
    "VariantType": "Repeat"
  },
  {
    "LocusId": "TA_repeats126",
    "LocusStructure": "(TA)*",
    "ReferenceRegion": "chr9:83177869-83177894",
    "VariantType": "Repeat"
  },
  {
    "LocusId": "TA_repeats127",
    "LocusStructure": "(TA)*",
    "ReferenceRegion": "chr9:83608432-83608465",
    "VariantType": "Repeat"
  },
  {
    "LocusId": "TA_repeats128",
    "LocusStructure": "(TA)*",
    "ReferenceRegion": "chr9:83608936-83608961",
    "VariantType": "Repeat"
  },
  {
    "LocusId": "TA_repeats129",
    "LocusStructure": "(TA)*",
    "ReferenceRegion": "chr9:84042600-84042649",
    "VariantType": "Repeat"
  },
  {
    "LocusId": "TA_repeats130",
    "LocusStructure": "(TA)*",
    "ReferenceRegion": "chr9:84126162-84126247",
    "VariantType": "Repeat"
  },
  {
    "LocusId": "TA_repeats131",
    "LocusStructure": "(TA)*",
    "ReferenceRegion": "chr9:84596496-84596584",
    "VariantType": "Repeat"
  },
  {
    "LocusId": "TA_repeats132",
    "LocusStructure": "(TA)*",
    "ReferenceRegion": "chr9:85102571-85102628",
    "VariantType": "Repeat"
  },
  {
    "LocusId": "TA_repeats133",
    "LocusStructure": "(TA)*",
    "ReferenceRegion": "chr9:85125305-85125481",
    "VariantType": "Repeat"
  },
  {
    "LocusId": "TA_repeats134",
    "LocusStructure": "(TA)*",
    "ReferenceRegion": "chr9:85623806-85623850",
    "VariantType": "Repeat"
  },
  {
    "LocusId": "TA_repeats135",
    "LocusStructure": "(TA)*",
    "ReferenceRegion": "chr9:85624042-85624153",
    "VariantType": "Repeat"
  },
  {
    "LocusId": "TA_repeats136",
    "LocusStructure": "(TA)*",
    "ReferenceRegion": "chr9:86122596-86122654",
    "VariantType": "Repeat"
  },
  {
    "LocusId": "TA_repeats137",
    "LocusStructure": "(TA)*",
    "ReferenceRegion": "chr9:87485012-87485280",
    "VariantType": "Repeat"
  },
  {
    "LocusId": "TA_repeats138",
    "LocusStructure": "(TA)*",
    "ReferenceRegion": "chr9:89796550-89796628",
    "VariantType": "Repeat"
  },
  {
    "LocusId": "TA_repeats139",
    "LocusStructure": "(TA)*",
    "ReferenceRegion": "chr9:91550842-91550887",
    "VariantType": "Repeat"
  },
  {
    "LocusId": "TA_repeats140",
    "LocusStructure": "(TA)*",
    "ReferenceRegion": "chr9:92136631-92136656",
    "VariantType": "Repeat"
  },
  {
    "LocusId": "TA_repeats141",
    "LocusStructure": "(TA)*",
    "ReferenceRegion": "chr9:92172086-92172172",
    "VariantType": "Repeat"
  },
  {
    "LocusId": "TA_repeats142",
    "LocusStructure": "(TA)*",
    "ReferenceRegion": "chr9:93357666-93357710",
    "VariantType": "Repeat"
  },
  {
    "LocusId": "TA_repeats143",
    "LocusStructure": "(TA)*",
    "ReferenceRegion": "chr9:96638150-96638189",
    "VariantType": "Repeat"
  },
  {
    "LocusId": "TA_repeats144",
    "LocusStructure": "(TA)*",
    "ReferenceRegion": "chr9:96640039-96640276",
    "VariantType": "Repeat"
  },
  {
    "LocusId": "TA_repeats145",
    "LocusStructure": "(TA)*",
    "ReferenceRegion": "chr9:98830211-98830353",
    "VariantType": "Repeat"
  },
  {
    "LocusId": "TA_repeats146",
    "LocusStructure": "(TA)*",
    "ReferenceRegion": "chr9:99543592-99543630",
    "VariantType": "Repeat"
  },
  {
    "LocusId": "TA_repeats147",
    "LocusStructure": "(TA)*",
    "ReferenceRegion": "chr9:101198562-101198689",
    "VariantType": "Repeat"
  },
  {
    "LocusId": "TA_repeats148",
    "LocusStructure": "(TA)*",
    "ReferenceRegion": "chr9:101897084-101897135",
    "VariantType": "Repeat"
  },
  {
    "LocusId": "TA_repeats149",
    "LocusStructure": "(TA)*",
    "ReferenceRegion": "chr9:102219126-102219166",
    "VariantType": "Repeat"
  },
  {
    "LocusId": "TA_repeats150",
    "LocusStructure": "(TA)*",
    "ReferenceRegion": "chr9:103158889-103158947",
    "VariantType": "Repeat"
  },
  {
    "LocusId": "TA_repeats151",
    "LocusStructure": "(TA)*",
    "ReferenceRegion": "chr9:103942376-103942426",
    "VariantType": "Repeat"
  },
  {
    "LocusId": "TA_repeats152",
    "LocusStructure": "(TA)*",
    "ReferenceRegion": "chr9:104228523-104228565",
    "VariantType": "Repeat"
  },
  {
    "LocusId": "TA_repeats153",
    "LocusStructure": "(TA)*",
    "ReferenceRegion": "chr9:104254094-104254130",
    "VariantType": "Repeat"
  },
  {
    "LocusId": "TA_repeats154",
    "LocusStructure": "(TA)*",
    "ReferenceRegion": "chr9:105154835-105154861",
    "VariantType": "Repeat"
  },
  {
    "LocusId": "TA_repeats155",
    "LocusStructure": "(TA)*",
    "ReferenceRegion": "chr9:105271875-105271970",
    "VariantType": "Repeat"
  },
  {
    "LocusId": "TA_repeats156",
    "LocusStructure": "(TA)*",
    "ReferenceRegion": "chr9:105575299-105575361",
    "VariantType": "Repeat"
  },
  {
    "LocusId": "TA_repeats157",
    "LocusStructure": "(TA)*",
    "ReferenceRegion": "chr9:105584195-105584310",
    "VariantType": "Repeat"
  },
  {
    "LocusId": "TA_repeats158",
    "LocusStructure": "(TA)*",
    "ReferenceRegion": "chr9:106131646-106131693",
    "VariantType": "Repeat"
  },
  {
    "LocusId": "TA_repeats159",
    "LocusStructure": "(TA)*",
    "ReferenceRegion": "chr9:106186134-106186205",
    "VariantType": "Repeat"
  },
  {
    "LocusId": "TA_repeats160",
    "LocusStructure": "(TA)*",
    "ReferenceRegion": "chr9:106187898-106187943",
    "VariantType": "Repeat"
  },
  {
    "LocusId": "TA_repeats161",
    "LocusStructure": "(TA)*",
    "ReferenceRegion": "chr9:106326426-106326564",
    "VariantType": "Repeat"
  },
  {
    "LocusId": "TA_repeats162",
    "LocusStructure": "(TA)*",
    "ReferenceRegion": "chr9:106327890-106328000",
    "VariantType": "Repeat"
  },
  {
    "LocusId": "TA_repeats163",
    "LocusStructure": "(TA)*",
    "ReferenceRegion": "chr9:106393673-106393704",
    "VariantType": "Repeat"
  },
  {
    "LocusId": "TA_repeats164",
    "LocusStructure": "(TA)*",
    "ReferenceRegion": "chr9:106395017-106395077",
    "VariantType": "Repeat"
  },
  {
    "LocusId": "TA_repeats165",
    "LocusStructure": "(TA)*",
    "ReferenceRegion": "chr9:106437466-106437539",
    "VariantType": "Repeat"
  },
  {
    "LocusId": "TA_repeats166",
    "LocusStructure": "(TA)*",
    "ReferenceRegion": "chr9:106807636-106807680",
    "VariantType": "Repeat"
  },
  {
    "LocusId": "TA_repeats167",
    "LocusStructure": "(TA)*",
    "ReferenceRegion": "chr9:107707067-107707109",
    "VariantType": "Repeat"
  },
  {
    "LocusId": "TA_repeats168",
    "LocusStructure": "(TA)*",
    "ReferenceRegion": "chr9:107757898-107758061",
    "VariantType": "Repeat"
  },
  {
    "LocusId": "TA_repeats169",
    "LocusStructure": "(TA)*",
    "ReferenceRegion": "chr9:107803938-107804093",
    "VariantType": "Repeat"
  },
  {
    "LocusId": "TA_repeats170",
    "LocusStructure": "(TA)*",
    "ReferenceRegion": "chr9:108669358-108669412",
    "VariantType": "Repeat"
  },
  {
    "LocusId": "TA_repeats171",
    "LocusStructure": "(TA)*",
    "ReferenceRegion": "chr9:109565890-109565947",
    "VariantType": "Repeat"
  },
  {
    "LocusId": "TA_repeats172",
    "LocusStructure": "(TA)*",
    "ReferenceRegion": "chr9:110068326-110068371",
    "VariantType": "Repeat"
  },
  {
    "LocusId": "TA_repeats173",
    "LocusStructure": "(TA)*",
    "ReferenceRegion": "chr9:111217370-111217658",
    "VariantType": "Repeat"
  },
  {
    "LocusId": "TA_repeats174",
    "LocusStructure": "(TA)*",
    "ReferenceRegion": "chr9:111505353-111505491",
    "VariantType": "Repeat"
  },
  {
    "LocusId": "TA_repeats175",
    "LocusStructure": "(TA)*",
    "ReferenceRegion": "chr9:111505526-111505604",
    "VariantType": "Repeat"
  },
  {
    "LocusId": "TA_repeats176",
    "LocusStructure": "(TA)*",
    "ReferenceRegion": "chr9:111511844-111511882",
    "VariantType": "Repeat"
  },
  {
    "LocusId": "TA_repeats177",
    "LocusStructure": "(TA)*",
    "ReferenceRegion": "chr9:113290358-113290467",
    "VariantType": "Repeat"
  },
  {
    "LocusId": "TA_repeats178",
    "LocusStructure": "(TA)*",
    "ReferenceRegion": "chr9:113421987-113422017",
    "VariantType": "Repeat"
  },
  {
    "LocusId": "TA_repeats179",
    "LocusStructure": "(TA)*",
    "ReferenceRegion": "chr9:114036668-114036718",
    "VariantType": "Repeat"
  },
  {
    "LocusId": "TA_repeats180",
    "LocusStructure": "(TA)*",
    "ReferenceRegion": "chr9:114293036-114293095",
    "VariantType": "Repeat"
  },
  {
    "LocusId": "TA_repeats181",
    "LocusStructure": "(TA)*",
    "ReferenceRegion": "chr9:116209596-116209641",
    "VariantType": "Repeat"
  },
  {
    "LocusId": "TA_repeats182",
    "LocusStructure": "(TA)*",
    "ReferenceRegion": "chr9:117705956-117706027",
    "VariantType": "Repeat"
  },
  {
    "LocusId": "TA_repeats183",
    "LocusStructure": "(TA)*",
    "ReferenceRegion": "chr9:118099577-118099608",
    "VariantType": "Repeat"
  },
  {
    "LocusId": "TA_repeats184",
    "LocusStructure": "(TA)*",
    "ReferenceRegion": "chr9:118820452-118820523",
    "VariantType": "Repeat"
  },
  {
    "LocusId": "TA_repeats185",
    "LocusStructure": "(TA)*",
    "ReferenceRegion": "chr9:119292373-119292430",
    "VariantType": "Repeat"
  },
  {
    "LocusId": "TA_repeats186",
    "LocusStructure": "(TA)*",
    "ReferenceRegion": "chr9:119882242-119882329",
    "VariantType": "Repeat"
  },
  {
    "LocusId": "TA_repeats187",
    "LocusStructure": "(TA)*",
    "ReferenceRegion": "chr9:119987810-119987854",
    "VariantType": "Repeat"
  },
  {
    "LocusId": "TA_repeats188",
    "LocusStructure": "(TA)*",
    "ReferenceRegion": "chr9:120805991-120806023",
    "VariantType": "Repeat"
  },
  {
    "LocusId": "TA_repeats189",
    "LocusStructure": "(TA)*",
    "ReferenceRegion": "chr9:120960471-120960632",
    "VariantType": "Repeat"
  },
  {
    "LocusId": "TA_repeats190",
    "LocusStructure": "(TA)*",
    "ReferenceRegion": "chr9:121029200-121029226",
    "VariantType": "Repeat"
  },
  {
    "LocusId": "TA_repeats191",
    "LocusStructure": "(TA)*",
    "ReferenceRegion": "chr9:121235145-121235187",
    "VariantType": "Repeat"
  },
  {
    "LocusId": "TA_repeats192",
    "LocusStructure": "(TA)*",
    "ReferenceRegion": "chr9:121255472-121255527",
    "VariantType": "Repeat"
  },
  {
    "LocusId": "TA_repeats193",
    "LocusStructure": "(TA)*",
    "ReferenceRegion": "chr9:121352589-121352598",
    "VariantType": "Repeat"
  },
  {
    "LocusId": "TA_repeats194",
    "LocusStructure": "(TA)*",
    "ReferenceRegion": "chr9:121354202-121354332",
    "VariantType": "Repeat"
  },
  {
    "LocusId": "TA_repeats195",
    "LocusStructure": "(TA)*",
    "ReferenceRegion": "chr9:121356013-121356040",
    "VariantType": "Repeat"
  },
  {
    "LocusId": "TA_repeats196",
    "LocusStructure": "(TA)*",
    "ReferenceRegion": "chr9:121674285-121674320",
    "VariantType": "Repeat"
  },
  {
    "LocusId": "TA_repeats197",
    "LocusStructure": "(TA)*",
    "ReferenceRegion": "chr9:121902692-121902786",
    "VariantType": "Repeat"
  },
  {
    "LocusId": "TA_repeats198",
    "LocusStructure": "(TA)*",
    "ReferenceRegion": "chr9:122129499-122129521",
    "VariantType": "Repeat"
  },
  {
    "LocusId": "TA_repeats199",
    "LocusStructure": "(TA)*",
    "ReferenceRegion": "chr9:122599462-122599510",
    "VariantType": "Repeat"
  },
  {
    "LocusId": "TA_repeats200",
    "LocusStructure": "(TA)*",
    "ReferenceRegion": "chr9:122649533-122649594",
    "VariantType": "Repeat"
  },
  {
    "LocusId": "TA_repeats201",
    "LocusStructure": "(TA)*",
    "ReferenceRegion": "chr9:122977666-122977725",
    "VariantType": "Repeat"
  },
  {
    "LocusId": "TA_repeats202",
    "LocusStructure": "(TA)*",
    "ReferenceRegion": "chr9:123764402-123764620",
    "VariantType": "Repeat"
  },
  {
    "LocusId": "TA_repeats203",
    "LocusStructure": "(TA)*",
    "ReferenceRegion": "chr9:124588432-124588620",
    "VariantType": "Repeat"
  },
  {
    "LocusId": "TA_repeats204",
    "LocusStructure": "(TA)*",
    "ReferenceRegion": "chr9:124588731-124588867",
    "VariantType": "Repeat"
  },
  {
    "LocusId": "TA_repeats205",
    "LocusStructure": "(TA)*",
    "ReferenceRegion": "chr9:125865861-125865916",
    "VariantType": "Repeat"
  },
  {
    "LocusId": "TA_repeats206",
    "LocusStructure": "(TA)*",
    "ReferenceRegion": "chr9:126994334-126994382",
    "VariantType": "Repeat"
  },
  {
    "LocusId": "TA_repeats207",
    "LocusStructure": "(TA)*",
    "ReferenceRegion": "chr9:127808475-127808503",
    "VariantType": "Repeat"
  },
  {
    "LocusId": "TA_repeats208",
    "LocusStructure": "(TA)*",
    "ReferenceRegion": "chr9:128455946-128456126",
    "VariantType": "Repeat"
  },
  {
    "LocusId": "TA_repeats209",
    "LocusStructure": "(TA)*",
    "ReferenceRegion": "chr9:128460454-128460628",
    "VariantType": "Repeat"
  },
  {
    "LocusId": "TA_repeats210",
    "LocusStructure": "(TA)*",
    "ReferenceRegion": "chr9:128555645-128555671",
    "VariantType": "Repeat"
  },
  {
    "LocusId": "TA_repeats211",
    "LocusStructure": "(TA)*",
    "ReferenceRegion": "chr9:129471954-129472034",
    "VariantType": "Repeat"
  },
  {
    "LocusId": "TA_repeats212",
    "LocusStructure": "(TA)*",
    "ReferenceRegion": "chr9:130360692-130360772",
    "VariantType": "Repeat"
  },
  {
    "LocusId": "TA_repeats213",
    "LocusStructure": "(TA)*",
    "ReferenceRegion": "chr9:130747942-130748028",
    "VariantType": "Repeat"
  },
  {
    "LocusId": "TA_repeats214",
    "LocusStructure": "(TA)*",
    "ReferenceRegion": "chr9:131496077-131496126",
    "VariantType": "Repeat"
  },
  {
    "LocusId": "TA_repeats215",
    "LocusStructure": "(TA)*",
    "ReferenceRegion": "chr9:131496424-131496482",
    "VariantType": "Repeat"
  },
  {
    "LocusId": "TA_repeats216",
    "LocusStructure": "(TA)*",
    "ReferenceRegion": "chr9:132002082-132002334",
    "VariantType": "Repeat"
  },
  {
    "LocusId": "TA_repeats217",
    "LocusStructure": "(TA)*",
    "ReferenceRegion": "chr9:134970808-134970961",
    "VariantType": "Repeat"
  },
  {
    "LocusId": "TA_repeats218",
    "LocusStructure": "(TA)*",
    "ReferenceRegion": "chr9:135361372-135361478",
    "VariantType": "Repeat"
  },
  {
    "LocusId": "TA_repeats219",
    "LocusStructure": "(TA)*",
    "ReferenceRegion": "chr9:135589661-135589688",
    "VariantType": "Repeat"
  },
  {
    "LocusId": "TA_repeats220",
    "LocusStructure": "(TA)*",
    "ReferenceRegion": "chr9:135590186-135590209",
    "VariantType": "Repeat"
  },
  {
    "LocusId": "TA_repeats221",
    "LocusStructure": "(TA)*",
    "ReferenceRegion": "chr9:136829144-136829191",
    "VariantType": "Repeat"
  },
  {
    "LocusId": "TA_repeats222",
    "LocusStructure": "(TA)*",
    "ReferenceRegion": "chr9:136829433-136829574",
    "VariantType": "Repeat"
  }
]
